fieldsurveys/__init__.py
fieldsurveys/keyfile.json
fieldsurveys/make_app.py
fieldsurveys/requirements.txt
fieldsurveys/survey.yaml
fieldsurveys/app_files/__init__.py
fieldsurveys/app_files/image_upload.py
fieldsurveys/app_files/navbar_utils.py
fieldsurveys/app_files/utils.py
tests/__init__.py
tests/test_image_upload.py
tests/test_playwright_test.py
tests/test_utils.py
fieldsurveys-1.0.3.dist-info/LICENSE
fieldsurveys-1.0.3.dist-info/METADATA
fieldsurveys-1.0.3.dist-info/WHEEL
fieldsurveys-1.0.3.dist-info/entry_points.txt
fieldsurveys-1.0.3.dist-info/top_level.txt
fieldsurveys-1.0.3.dist-info/RECORD
