Metadata-Version: 2.1
Name: fieldsurveys
Version: 1.0.3
Summary: A Python package for creating and managing field surveys.
Home-page: https://github.com/karangattu/fieldsurveys
Author: Karan Gathani
Author-email: karan.gathani+fieldsurveysapp@posit.co
License-File: LICENSE
Requires-Dist: beautifulsoup4==4.12.3
Requires-Dist: cryptography==43.0.1
Requires-Dist: faicons==0.2.2
Requires-Dist: geopy==2.4.1
Requires-Dist: gspread==6.1.2
Requires-Dist: gspread-dataframe==4.0.0
Requires-Dist: htmltools==0.5.3
Requires-Dist: pandas==2.2.3
Requires-Dist: plotly==5.24.1
Requires-Dist: pytz==2024.2
Requires-Dist: PyYAML==6.0.2
Requires-Dist: requests==2.32.3
Requires-Dist: rsconnect-python==1.24.0
Requires-Dist: shiny==1.1.0
Requires-Dist: shinyswatch==0.7.0
Requires-Dist: timezonefinder==6.5.3
Requires-Dist: us==3.2.0
Requires-Dist: Wikipedia-API==0.7.1
Requires-Dist: google-api-python-client==2.151.0
Provides-Extra: tests
Requires-Dist: playwright==1.47.0; extra == "tests"
Requires-Dist: pytest==8.3.3; extra == "tests"
Requires-Dist: pytest-mock==3.14.0; extra == "tests"
Requires-Dist: pytest-playwright==0.5.2; extra == "tests"
